nile_greet/__init__.py
nile_greet/main.py
nile_greet-0.1.0.dist-info/entry_points.txt
nile_greet-0.1.0.dist-info/WHEEL
nile_greet-0.1.0.dist-info/METADATA
nile_greet-0.1.0.dist-info/RECORD
