Metadata-Version: 2.1
Name: nile-greet
Version: 0.1.0
Summary: Nile plugin for greeting
License: MIT
Author: Fran Algaba
Author-email: f.algaba.work@gmail.com
Requires-Python: >=3.7.11,<4.0.0
Classifier: Development Status :: 3 - Alpha
Classifier: Intended Audience :: Developers
Classifier: License :: OSI Approved :: MIT License
Classifier: Operating System :: OS Independent
Classifier: Programming Language :: Python :: 3
Classifier: Programming Language :: Python :: 3.10
Classifier: Programming Language :: Python :: 3.8
Classifier: Programming Language :: Python :: 3.9
Classifier: Topic :: Software Development :: Libraries :: Python Modules
Requires-Dist: click (>=8.0.4,<9.0.0)
